statsplotly/__init__.py
statsplotly/_base.py
statsplotly/_plotting/__init__.py
statsplotly/_plotting/_barplot.py
statsplotly/_plotting/_catplot.py
statsplotly/_plotting/_distplot.py
statsplotly/_plotting/_heatmap.py
statsplotly/_plotting/_jointplot.py
statsplotly/_plotting/_plot.py
statsplotly/_plotting/helpers.py
statsplotly/constants.py
statsplotly/exceptions.py
statsplotly/plot_objects/__init__.py
statsplotly/plot_objects/layout/__init__.py
statsplotly/plot_objects/layout/_axis.py
statsplotly/plot_objects/layout/_layout.py
statsplotly/plot_objects/trace.py
statsplotly/plot_specifiers/__init__.py
statsplotly/plot_specifiers/color/__init__.py
statsplotly/plot_specifiers/color/_core.py
statsplotly/plot_specifiers/color/_utils.py
statsplotly/plot_specifiers/common.py
statsplotly/plot_specifiers/data/__init__.py
statsplotly/plot_specifiers/data/_core.py
statsplotly/plot_specifiers/data/_utils.py
statsplotly/plot_specifiers/data/statistics.py
statsplotly/plot_specifiers/figure/__init__.py
statsplotly/plot_specifiers/figure/_core.py
statsplotly/plot_specifiers/figure/_utils.py
statsplotly/plot_specifiers/layout/__init__.py
statsplotly/plot_specifiers/layout/_core.py
statsplotly/plot_specifiers/layout/_utils.py
statsplotly/plot_specifiers/trace.py
statsplotly/utils.py
statsplotly-0.3.0.dist-info/LICENSE
statsplotly-0.3.0.dist-info/METADATA
statsplotly-0.3.0.dist-info/WHEEL
statsplotly-0.3.0.dist-info/RECORD
