Metadata-Version: 2.3
Name: statsplotly
Version: 0.3.0
Summary: Tidy API for statistical visualization with Plotly
License: BSD-3-Clause
Author: Benjamin Roland
Author-email: benjamin.roland@hotmail.fr
Requires-Python: >=3.10,<3.14
Classifier: License :: OSI Approved :: BSD License
Classifier: Programming Language :: Python :: 3
Classifier: Programming Language :: Python :: 3.10
Classifier: Programming Language :: Python :: 3.11
Classifier: Programming Language :: Python :: 3.12
Classifier: Programming Language :: Python :: 3.13
Requires-Dist: pandas (>=1.5.0)
Requires-Dist: plotly (>=5.19.0,<6.0.0)
Requires-Dist: pydantic (>=2.6.2,<3.0.0)
Requires-Dist: scipy (>=1.11.1,<2.0.0)
Requires-Dist: seaborn (>=0.13.2,<0.14.0)
Project-URL: Documentation, https://parici75.github.io/statsplotly/
Project-URL: Homepage, https://github.com/parici75/statsplotly
